[
  {
    "id": 28399,
    "owner_address": "CtxHhwboVTtRf1kC4Zwfz8Zf8bNW78N2uuR3oZX5VFKb",
    "token_address": "9raUVuzeWUk53co63M4WXLWPWE4Xc6Lpn7RS9dnkpump",
    "token_account_address": null,
    "v2ex_username": "Pump.fun AMM (V2EX-WSOL) Pool",
    "avatar_url": null,
    "hold_rank": 2,
    "hold_amount": 50362449.801971,
    "decimals": 6,
    "hold_percentage": 5.0362449801971,
    "rank_delta": 0,
    "amount_delta": -499498.913459,
    "changed_at": "2026-06-24 23:30:43"
  },
  {
    "id": 28371,
    "owner_address": "7j8RCpqZJzQbCwzPPaDWpoHa9mFx7GL2Km4Fsfws7TKG",
    "token_address": "9raUVuzeWUk53co63M4WXLWPWE4Xc6Lpn7RS9dnkpump",
    "token_account_address": null,
    "v2ex_username": "Meteora (V2EX-WSOL) Market",
    "avatar_url": null,
    "hold_rank": 9,
    "hold_amount": 5022317.984297,
    "decimals": 6,
    "hold_percentage": 0.5022317984297,
    "rank_delta": 1,
    "amount_delta": -1531.660332,
    "changed_at": "2026-06-24 22:30:42"
  },
  {
    "id": 28400,
    "owner_address": "AK6uWWUpB8SsG4bKiPuCKmX8W8chRk9ezZbojMHVDwGF",
    "token_address": "9raUVuzeWUk53co63M4WXLWPWE4Xc6Lpn7RS9dnkpump",
    "token_account_address": null,
    "v2ex_username": "Meteora (V2EX-PUMP) Market",
    "avatar_url": null,
    "hold_rank": 11,
    "hold_amount": 4869287.949168,
    "decimals": 6,
    "hold_percentage": 0.4869287949168,
    "rank_delta": -2,
    "amount_delta": -184095.152615,
    "changed_at": "2026-06-24 23:30:43"
  },
  {
    "id": 28375,
    "owner_address": "4JBz4tAKgAmxjDPHHi9HRLj14RsCQJyuCkCFKnpz7B9s",
    "token_address": "9raUVuzeWUk53co63M4WXLWPWE4Xc6Lpn7RS9dnkpump",
    "token_account_address": null,
    "v2ex_username": "Livid",
    "avatar_url": null,
    "hold_rank": 16,
    "hold_amount": 2748029.900651,
    "decimals": 6,
    "hold_percentage": 0.2748029900651,
    "rank_delta": 0,
    "amount_delta": 2376.151027,
    "changed_at": "2026-06-24 22:30:42"
  },
  {
    "id": 28379,
    "owner_address": "BYS2b1FGbYAd12EBz6Ln88Kg81aQD3htyhzN8g8aN8R7",
    "token_address": "9raUVuzeWUk53co63M4WXLWPWE4Xc6Lpn7RS9dnkpump",
    "token_account_address": null,
    "v2ex_username": "crocoBaby",
    "avatar_url": null,
    "hold_rank": 26,
    "hold_amount": 1525954.860616,
    "decimals": 6,
    "hold_percentage": 0.1525954860616,
    "rank_delta": 1,
    "amount_delta": 47217.86022,
    "changed_at": "2026-06-24 22:30:42"
  },
  {
    "id": 28401,
    "owner_address": "25zhMDrj4J7rnfRgJZza9ahKCj4naTQXjqivDXLj93jX",
    "token_address": "9raUVuzeWUk53co63M4WXLWPWE4Xc6Lpn7RS9dnkpump",
    "token_account_address": null,
    "v2ex_username": "sugost",
    "avatar_url": null,
    "hold_rank": 35,
    "hold_amount": 1083069.368086,
    "decimals": 6,
    "hold_percentage": 0.10830693680859999,
    "rank_delta": -16,
    "amount_delta": -1070930.442516,
    "changed_at": "2026-06-24 23:30:43"
  }
]